ballsort/__init__.py
ballsort/ball_control.py
ballsort/ball_control_ch2.py
ballsort/ball_control_ch4.py
ballsort/ball_control_sim.py
ballsort/ballsort_display_utils.py
ballsort/ch0_scenario.py
ballsort/ch10_scenario.py
ballsort/ch11_scenario.py
ballsort/ch12_scenario.py
ballsort/ch13_scenario.py
ballsort/ch14_scenario.py
ballsort/ch1_scenario.py
ballsort/ch2_scenario.py
ballsort/ch2_state_manager.py
ballsort/ch3_scenario.py
ballsort/ch4_scenario.py
ballsort/ch4_state_manager.py
ballsort/ch4_state_validator.py
ballsort/ch5_scenario.py
ballsort/ch6_scenario.py
ballsort/ch7_scenario.py
ballsort/ch8_scenario.py
ballsort/ch9_scenario.py
ballsort/control_factory.py
ballsort/postmessage_update_reporter.py
ballsort/reveal_action.py
ballsort/reveal_color_value_action.py
ballsort/scenario.py
ballsort/scenario_control.py
ballsort/state_manager.py
ballsort/state_update_model.py
ballsort/state_utils.py
ballsort/state_validator.py
ballsort/update_reporter.py
ballsort-1.0.14.dist-info/LICENSE
ballsort-1.0.14.dist-info/METADATA
ballsort-1.0.14.dist-info/WHEEL
ballsort-1.0.14.dist-info/top_level.txt
ballsort-1.0.14.dist-info/RECORD
