Metadata-Version: 2.1
Name: ballsort
Version: 1.0.14
Summary: A framework for learning async Python
Author-email: Anders Heed <aheed88888@gmail.com>
Project-URL: Homepage, https://github.com/aheed/ballsort-framework
Classifier: Programming Language :: Python :: 3
Classifier: License :: OSI Approved :: MIT License
Classifier: Operating System :: OS Independent
Requires-Python: >=3.10
License-File: LICENSE
